deepsardl/__init__.py
deepsardl/__main__.py
deepsardl/cli/__init__.py
deepsardl/cli/generate_meta.py
deepsardl/cli/inference_script.py
deepsardl/cli/metrics_script.py
deepsardl/cli/preprocess_script.py
deepsardl/cli/train_script.py
deepsardl/config_preprocess.yml
deepsardl/example.py
deepsardl/inference/__init__.py
deepsardl/input/__init__.py
deepsardl/networks/UNet.py
deepsardl/networks/__init__.py
deepsardl/networks/mlp.py
deepsardl/networks/models.py
deepsardl/plotting/__init__.py
deepsardl/preprocessing/__init__.py
deepsardl/preprocessing/lib_netcdf.py
deepsardl/preprocessing/patches.py
deepsardl/train/__init__.py
deepsardl/utils/__init__.py
deepsardl/utils/aux_utils.py
deepsardl/utils/preprocess_utils.py
deepsardl-0.1.0a2.dist-info/entry_points.txt
deepsardl-0.1.0a2.dist-info/LICENSE
deepsardl-0.1.0a2.dist-info/WHEEL
deepsardl-0.1.0a2.dist-info/METADATA
deepsardl-0.1.0a2.dist-info/RECORD
