Metadata-Version: 2.1
Name: deepsardl
Version: 0.1.0a2
Summary: This is a main package for processeing data for DeepSAR
Home-page: https://github.com/DeepSAR/deepsardl
License: MIT
Author: DeepSAR
Author-email: DeepSAR@imansour.net
Requires-Python: >=3.8,<3.10
Classifier: Development Status :: 3 - Alpha
Classifier: Intended Audience :: Developers
Classifier: License :: OSI Approved :: MIT License
Classifier: Operating System :: OS Independent
Classifier: Programming Language :: Python :: 3
Classifier: Programming Language :: Python :: 3.8
Classifier: Programming Language :: Python :: 3.9
Classifier: Topic :: Software Development :: Libraries :: Python Modules
Requires-Dist: PyYAML (>=6.0,<7.0)
Requires-Dist: astropy (>=5.0,<6.0)
Requires-Dist: dask (>=2022.1.0,<2023.0.0)
Requires-Dist: geopandas (>=0.10.2,<0.11.0)
Requires-Dist: graphviz (>=0.19,<0.20)
Requires-Dist: h5netcdf (>=0.11,<0.14)
Requires-Dist: importlib_metadata (>=4.10.1,<5.0.0); python_version < "3.8"
Requires-Dist: ipykernel (>=6.7.0,<7.0.0)
Requires-Dist: natsort (>=8.0.2,<9.0.0)
Requires-Dist: netCDF4 (>=1.5.8,<2.0.0)
Requires-Dist: numba (>=0.54.1,<0.56.0)
Requires-Dist: pydot (>=1.4.2,<2.0.0)
Requires-Dist: rasterio (>=1.2.10,<2.0.0)
Requires-Dist: rich (>=10.14.0,<11.0.0)
Requires-Dist: rioxarray (>=0.9.0,<0.10.0)
Requires-Dist: scikit-image (>=0.19.1,<0.20.0)
Requires-Dist: scikit-learn (>=1.0.2,<2.0.0)
Requires-Dist: seaborn (>=0.11.2,<0.12.0)
Requires-Dist: tables (>=3.6.1,<4.0.0)
Requires-Dist: tensorboard (>=2.7.0,<3.0.0)
Requires-Dist: tensorflow (>=2.7.0,<3.0.0)
Requires-Dist: torch (>=1.10.0,<2.0.0)
Requires-Dist: torchvision (>=0.11.1,<0.12.0)
Requires-Dist: typer[all] (>=0.4.0,<0.5.0)
Requires-Dist: xarray (>=0.20.2,<0.21.0)
Project-URL: Repository, https://github.com/DeepSAR/deepsardl
